certbot_dns_domainoffensive/__init__.py
certbot_dns_domainoffensive/dns_domainoffensive.py
certbot_dns_domainoffensive-2.0.0.dist-info/LICENSE.txt
certbot_dns_domainoffensive-2.0.0.dist-info/METADATA
certbot_dns_domainoffensive-2.0.0.dist-info/WHEEL
certbot_dns_domainoffensive-2.0.0.dist-info/entry_points.txt
certbot_dns_domainoffensive-2.0.0.dist-info/top_level.txt
certbot_dns_domainoffensive-2.0.0.dist-info/RECORD
