Metadata-Version: 2.1
Name: certbot-dns-domainoffensive
Version: 2.0.0
Summary: Domain-Offensive DNS Authenticator plugin for Certbot
Home-page: https://github.com/domainoffensive/certbot-dns-domainoffensive
Author: Domain-Offensive
License: Apache License 2.0
Classifier: Development Status :: 5 - Production/Stable
Classifier: Environment :: Plugins
Classifier: Intended Audience :: System Administrators
Classifier: License :: OSI Approved :: Apache Software License
Classifier: Operating System :: POSIX :: Linux
Classifier: Programming Language :: Python
Classifier: Programming Language :: Python :: 3
Classifier: Programming Language :: Python :: 3.7
Classifier: Programming Language :: Python :: 3.8
Classifier: Programming Language :: Python :: 3.9
Classifier: Programming Language :: Python :: 3.10
Classifier: Programming Language :: Python :: 3.11
Classifier: Topic :: Internet :: WWW/HTTP
Classifier: Topic :: Security
Classifier: Topic :: System :: Installation/Setup
Classifier: Topic :: System :: Networking
Classifier: Topic :: System :: Systems Administration
Classifier: Topic :: Utilities
Requires-Python: >=2.7, !=3.0.*, !=3.1.*, !=3.2.*, !=3.3.*
License-File: LICENSE.txt
Requires-Dist: acme >=2.0.0
Requires-Dist: certbot >=2.0.0
Requires-Dist: requests
Requires-Dist: setuptools
Requires-Dist: zope.interface
Provides-Extra: docs
Requires-Dist: Sphinx >=1.0 ; extra == 'docs'
Requires-Dist: sphinx-rtd-theme ; extra == 'docs'
